Metadata-Version: 1.0
Name: cnemri-distributions
Version: 0.2
Summary: Gaussian and Binomial distributions
Home-page: UNKNOWN
Author: Chouaieb, Nemri <chouaib.nemri@gmail.com>
Author-email: UNKNOWN
License: UNKNOWN
Platform: UNKNOWN
